dice_rolling
