Metadata-Version: 2.1
Name: dice-rolling
Version: 1.1.0
Summary: Module to roll multiple dice.
Home-page: https://github.com/Ajordat/dice_roller
Author: Ajordat
Author-email: alexjortri@gmail.com
License: MIT
Platform: UNKNOWN
Classifier: License :: OSI Approved :: MIT License
Classifier: Programming Language :: Python :: 3.8
Classifier: Programming Language :: Python :: 3.7
